yanico/__init__.py
yanico/__main__.py
yanico/config.py
yanico/command/__init__.py
yanico/session/__init__.py
yanico/session/firefox.py
yanico/session/token.py
yanico-0.3.0.dist-info/licenses/LICENSE
yanico-0.3.0.dist-info/METADATA
yanico-0.3.0.dist-info/WHEEL
yanico-0.3.0.dist-info/entry_points.txt
yanico-0.3.0.dist-info/top_level.txt
yanico-0.3.0.dist-info/RECORD
