Metadata-Version: 2.4
Name: yanico
Version: 0.3.0
Summary: Yet Another Niconico-douga Command-line Interface
Author-email: Masayuki Yamamoto <15698961+ma8ma@users.noreply.github.com>
License:                                  Apache License
Project-URL: Homepage, https://github.com/ma8ma/yanico
Project-URL: Repository, https://github.com/ma8ma/yanico
Project-URL: Changelog, https://github.com/ma8ma/yanico/blob/master/CHANGES.ja.md
Keywords: cli,comment,niconico,video
Classifier: Development Status :: 3 - Alpha
Classifier: Environment :: Console
Classifier: Intended Audience :: End Users/Desktop
Classifier: License :: OSI Approved :: Apache Software License
Classifier: Operating System :: POSIX
Classifier: Programming Language :: Python
Classifier: Programming Language :: Python :: 3
Classifier: Programming Language :: Python :: 3.10
Classifier: Programming Language :: Python :: 3.11
Classifier: Programming Language :: Python :: 3.12
Classifier: Programming Language :: Python :: 3.13
Classifier: Programming Language :: Python :: 3.14
Classifier: Topic :: Internet :: WWW/HTTP
Classifier: Topic :: Internet :: WWW/HTTP :: Session
Requires-Python: >=3.10
License-File: LICENSE
Provides-Extra: develop
Requires-Dist: hacking; extra == "develop"
Requires-Dist: flake8-docstrings; extra == "develop"
Requires-Dist: pep8-naming; extra == "develop"
Provides-Extra: dev
Requires-Dist: black>=23.7.0; extra == "dev"
Requires-Dist: coverage; extra == "dev"
Requires-Dist: docutils>=0.21; extra == "dev"
Requires-Dist: mypy>=0.560; extra == "dev"
Requires-Dist: pylint>=2.6.0; extra == "dev"
Requires-Dist: pytest; extra == "dev"
Requires-Dist: setuptools>=61.0; extra == "dev"
Requires-Dist: types-setuptools; extra == "dev"
Dynamic: license-file
